fbadmin
