Metadata-Version: 1.1
Name: fbadmin
Version: 0.1.0.3
Summary: A python library to automate facebook group administration
Home-page: https://github.com/thekindlyone/fbadmin
Author: thekindlyone
Author-email: dodo.dodder@gmail.com
License: GNU GPL v2
Platform: UNKNOWN
Classifier: Development Status :: 4 - Beta
Classifier: Topic :: Utilities
Classifier: License :: OSI Approved :: GNU General Public License v2 or later (GPLv2+)
Classifier: Operating System :: OS Independent
Classifier: Programming Language :: Python :: 2.7
